{
  "neoforge:conditions": [
    {
      "type": "neoforge:not",
      "value": {
        "type": "neoforge:tag_empty",
        "tag": "c:foods/raw_seafood"
      }
    }
  ],
  "type": "farmersdelight:cooking",
  "experience": 1.0,
  "ingredients": [
    {
      "item": "eidolon_edoni:curry_chunk"
    },
    {
      "tag": "eidolon_edoni:seafood_curry_spices"
    },
    {
      "tag": "c:foods/raw_seafood"
    },
    {
      "tag": "c:foods/raw_seafood"
    },
    {
      "tag": "c:foods/vegetable"
    }
  ],
  "recipe_book_tab": "meals",
  "result": {
    "count": 1,
    "id": "eidolon_edoni:seafood_curry"
  }
}